README.rst
allowedsites.py
setup.py
django_allowedsites.egg-info/PKG-INFO
django_allowedsites.egg-info/SOURCES.txt
django_allowedsites.egg-info/dependency_links.txt
django_allowedsites.egg-info/not-zip-safe
django_allowedsites.egg-info/requires.txt
django_allowedsites.egg-info/top_level.txt